deepview_profile/__init__.py
deepview_profile/__main__.py
deepview_profile/analysis/__init__.py
deepview_profile/analysis/request_manager.py
deepview_profile/analysis/runner.py
deepview_profile/analysis/session.py
deepview_profile/analysis/static.py
deepview_profile/commands/__init__.py
deepview_profile/commands/analysis.py
deepview_profile/commands/interactive.py
deepview_profile/commands/measurements.py
deepview_profile/commands/memory.py
deepview_profile/commands/prediction_models.py
deepview_profile/commands/time.py
deepview_profile/config/__init__.py
deepview_profile/data/__init__.py
deepview_profile/data/hints.yml
deepview_profile/db/__init__.py
deepview_profile/db/database.py
deepview_profile/energy/__init__.py
deepview_profile/energy/measurer.py
deepview_profile/error_printing.py
deepview_profile/evaluate.py
deepview_profile/exceptions.py
deepview_profile/export_converter.py
deepview_profile/initialization.py
deepview_profile/io/__init__.py
deepview_profile/io/connection.py
deepview_profile/io/connection_acceptor.py
deepview_profile/io/connection_manager.py
deepview_profile/io/sentinel.py
deepview_profile/lru_cache.py
deepview_profile/models/__init__.py
deepview_profile/models/analysis.py
deepview_profile/models/source_map.py
deepview_profile/nvml.py
deepview_profile/pl/deepview_callback.py
deepview_profile/pl/deepview_interface.py
deepview_profile/profiler/__init__.py
deepview_profile/profiler/autograd.py
deepview_profile/profiler/backward.py
deepview_profile/profiler/ddp.py
deepview_profile/profiler/iteration.py
deepview_profile/profiler/operation.py
deepview_profile/profiler/utilization.py
deepview_profile/protocol/__init__.py
deepview_profile/protocol/message_handler.py
deepview_profile/protocol/message_sender.py
deepview_profile/protocol_gen/__init__.py
deepview_profile/protocol_gen/innpv_pb2.py
deepview_profile/pytorch_profiler_log_reader.py
deepview_profile/server.py
deepview_profile/skyline.py
deepview_profile/tests/__init__.py
deepview_profile-0.14.5.dist-info/LICENSE
deepview_profile-0.14.5.dist-info/METADATA
deepview_profile-0.14.5.dist-info/NOTICE
deepview_profile-0.14.5.dist-info/WHEEL
deepview_profile-0.14.5.dist-info/entry_points.txt
deepview_profile-0.14.5.dist-info/RECORD
