Metadata-Version: 2.1
Name: deepview-profile
Version: 0.14.5
Summary: Interactive performance profiling and debugging tool for PyTorch neural networks.
Home-page: https://github.com/CentML/DeepView.Profile
License: Apache-2.0
Keywords: pytorch,neural networks,debugger,profiler
Author: CentML
Author-email: support@centml.ai
Requires-Python: >=3.9,<4.0
Classifier: Development Status :: 4 - Beta
Classifier: Intended Audience :: Developers
Classifier: License :: OSI Approved :: Apache Software License
Classifier: Programming Language :: Python :: 3
Classifier: Programming Language :: Python :: 3.9
Classifier: Programming Language :: Python :: 3.10
Classifier: Programming Language :: Python :: 3.11
Classifier: Programming Language :: Python :: 3.12
Classifier: Programming Language :: Python :: 3.13
Classifier: Programming Language :: Python :: 3 :: Only
Classifier: Topic :: Software Development :: Debuggers
Requires-Dist: deepview-predict
Requires-Dist: numpy (>=1.15.2,<2.0.0)
Requires-Dist: nvidia-ml-py3
Requires-Dist: orjson
Requires-Dist: perfetto
Requires-Dist: protobuf (==3.19.6)
Requires-Dist: pyRAPL (>=0.2.3,<0.3.0)
Requires-Dist: pymongo
Requires-Dist: pyyaml
Requires-Dist: scipy
Requires-Dist: termcolor
Requires-Dist: toml (>=0.10.2,<0.11.0)
Requires-Dist: torch (>=2.1.0)
Requires-Dist: torch-tb-profiler
Project-URL: Repository, https://github.com/CentML/DeepView.Profile
